.dockerignore
.flake8
.gitignore
.travis.yml
CONTRIBUTING.md
Dockerfile
LICENSE
MANIFEST.in
README.pypi.rst
README.rst
README.txt
STYLE.md
configtest_dev.py
constraints.txt
convert_error_code.py
dev-requirements.txt
dev_glue.py
ez_setup.py
ga2sam_dev.py
ga2vcf_dev.py
readthedocs.yml
repo_dev.py
requirements.txt
server_dev.py
setup.py
.whiskey/action_hooks/pre-build
deploy/001-ga4gh.conf
deploy/application.wsgi
deploy/config.py
docs/Makefile
docs/conf.py
docs/configuration.rst
docs/datarepo.rst
docs/demo.rst
docs/development.rst
docs/environment.yml
docs/index.rst
docs/installation.rst
docs/introduction.rst
docs/ref_server_profiling.rst
docs/status.rst
docs/_static/logo_ga.png
docs/images/Consent_screen_-_ga4gh.png
docs/images/Create_project.png
docs/images/Credentials_-_ga4gh.png
docs/images/Credentials_-_ga4gh_2.png
docs/images/Credentials_-_ga4gh_3.png
ga4gh/__init__.py
ga4gh.egg-info/PKG-INFO
ga4gh.egg-info/SOURCES.txt
ga4gh.egg-info/dependency_links.txt
ga4gh.egg-info/entry_points.txt
ga4gh.egg-info/namespace_packages.txt
ga4gh.egg-info/not-zip-safe
ga4gh.egg-info/requires.txt
ga4gh.egg-info/top_level.txt
ga4gh/server/__init__.py
ga4gh/server/_version.py
ga4gh/server/backend.py
ga4gh/server/configtest.py
ga4gh/server/converters.py
ga4gh/server/datarepo.py
ga4gh/server/exceptions.py
ga4gh/server/frontend.py
ga4gh/server/gff3.py
ga4gh/server/paging.py
ga4gh/server/protocol.py
ga4gh/server/serverconfig.py
ga4gh/server/sqlite_backend.py
ga4gh/server/stuff.cfg
ga4gh/server/auth/__init__.py
ga4gh/server/cli/__init__.py
ga4gh/server/cli/configtest.py
ga4gh/server/cli/ga2sam.py
ga4gh/server/cli/ga2vcf.py
ga4gh/server/cli/repomanager.py
ga4gh/server/cli/server.py
ga4gh/server/datamodel/__init__.py
ga4gh/server/datamodel/bio_metadata.py
ga4gh/server/datamodel/datasets.py
ga4gh/server/datamodel/genotype_phenotype.py
ga4gh/server/datamodel/genotype_phenotype_featureset.py
ga4gh/server/datamodel/obo_parser.py
ga4gh/server/datamodel/ontologies.py
ga4gh/server/datamodel/reads.py
ga4gh/server/datamodel/references.py
ga4gh/server/datamodel/rna_quantification.py
ga4gh/server/datamodel/sequence_annotations.py
ga4gh/server/datamodel/variants.py
ga4gh/server/repo/__init__.py
ga4gh/server/repo/rnaseq2ga.py
